[
    {
        "Q": "如何使用餐券？",
        "A": "購買餐券後，系統會發送電子票券至會員帳號或Email，至餐廳消費時出示即可使用。"
    },
    {
        "Q": "餐券會有使用期限嗎？",
        "A": "有，期限會在購買前的商品資訊與電子票券上明確標示。"
    },
    {
        "Q": "餐券可以退費或轉讓嗎？",
        "A": "除非餐廳無法提供服務或依平台退費政策規定，餐券一般不接受退費與轉讓。"
    },
    {
        "Q": "餐券購買後多久才會收到？",
        "A": "付款完成後通常立即發送電子餐券，特殊活動票券可能需1–2個工作天處理。"
    },
    {
        "Q": "如何查詢我購買過的餐券？",
        "A": "登入會員中心後可於「我的餐券」頁面查看所有購買紀錄與使用狀態。"
    },
    {
        "Q": "如何修改或取消訂位嗎？",
        "A": "可於訂位紀錄中進行修改或取消。"
    },
    {
        "Q": "聯絡客服？",
        "A": "您可以透過網站下方的「聯絡我們」頁面填寫表單，或寄信至 service@gourmetmap.com，我們會盡快回覆。",
        "action": "redirect",
        "target": "/customerServices"
    },
    {
        "Q": "如果有被黑名單怎麼辦？",
        "A": "請先透過網站下方的「聯絡我們」頁面填寫表單，或寄信至 service@gourmetmap.com，我們會盡快釐清您被黑名單的原因，並協助您處理相關事宜。",
        "action": "redirect",
        "target": "/customerServices"
    },
    {
        "Q": "登入？",
        "A": "已經幫您導向登入與註冊的頁面囉! 也可以擊下方按鈕前往登入與註冊頁面!",
        "action": "redirect",
        "target": "/login"
    },
    {
        "Q": "註冊？",
        "A": "已經幫您導向登入與註冊的頁面囉! 也可以擊下方按鈕前往登入與註冊頁面!",
        "action": "redirect",
        "target": "/login"
    },
    {
        "Q": "忘記密碼怎麼辦？",
        "A": "已經幫您導向更正密碼頁面囉! 也可以擊下方按鈕前往忘記密碼頁面!",
        "action": "redirect",
        "target": "/forgot-password"
    },
    {
        "Q": "幫我登出",
        "A": "已經幫您登出囉! 期待您再度光臨!",
        "action": "redirect",
        "target": "/logout"
    },
    {
        "Q": "吳俊德是誰？",
        "A": "俊德是一位超級可靠的夥伴，做事細心又有責任感。每次專案遇到問題，他總能冷靜分析、找到最有效的解法。他不只技術實力強，還會主動幫助同學，是團隊裡的定心丸！"
    },
    {
        "Q": "我的收藏",
        "A": "這邊是您的收藏頁面，我已幫您導向囉！",
        "action": "redirect",
        "target": "/member/favorite"
    },
    {
        "Q": "我的訂位",
        "A": "這邊是您的訂位頁面，我已幫您導向囉！",
        "action": "redirect",
        "target": "/reservationRecords"
    }
]